{
    "title": "الأموات",
    "author": "جيمس جويس",
    "edition": "الطبعة الأولى: 2019",
    "category": "أدب",
    "subcategory": "قصة",
    "quote": "كانَت ليلي، ابنةُ القيِّم، تُهرَبُ من خطواتِها بإثمِ معنى الكلمة.",
    "summary": "نصٌّ قصصيّ يدور في أجواء أمسيةٍ اجتماعية/احتفالية داخل بيتٍ في دبلن، حيث تُرصد تفاصيل الحركة والضيافة والطقوس الصغيرة التي تبدو عادية لكنها تكشف طبقاتٍ خفية من العلاقات.\nيُقدِّم السرد شخصياتٍ تتقاطع عبر واجبات الخدمة والضيوف والذكريات المتداولة، مع توترٍ لطيف بين ما يُقال في العلن وما يُحسّ في الداخل، وما تصنعه العادة من ثقلٍ على النفوس.\nيتحوّل الاحتفال تدريجياً إلى مساحة لاستحضار الماضي ومساءلة الحاضر، بحيث يصبح «الاجتماع» مرآةً للزمن وللغيابات، ويغدو الحيّ محاطاً بأصداء من رحلوا وبما تركوه في الوجدان.",
    "footprint": [
        "إبراز كيف يمكن للتفاصيل اليومية والطقوس الاجتماعية أن تكشف البنية العاطفية العميقة للعلاقات.",
        "تنبيه القارئ إلى أثر الذاكرة والغياب في تشكيل نظرتنا للحب والواجب والانتماء.",
        "تقديم نموذج سردي يقوم على الرصد النفسي الهادئ وبناء الدلالة عبر الإيحاء لا التصريح."
    ],
    "hashtags": [
        "#الأموات",
        "#جيمس_جويس"
    ],
    "mood": "🕯️ تأملي حزين",
    "pacing": "بطيء وتأملي",
    "complexity": "عميق يحتاج تركيز",
    "interview": "س: لماذا وضعتَ حدثاً احتفالياً في قلب القصة؟ ج: لأن الاحتفال يكشف الأقنعة بسرعة؛ في الزحام يظهر ما نخفيه عن أنفسنا.\nس: ما الفكرة الأشد حضوراً خلف التفاصيل؟ ج: أن الماضي لا يمرّ؛ إنه يتكلم داخلنا كلما ظننا أننا نعيش الحاضر فقط.\nس: ما الذي تريده من القارئ بعد الصفحة الأخيرة؟ ج: أن ينصت للصمت بين الكلمات، فهناك تُقال الحقيقة.",
    "pages": "96",
    "quality": "مقبولة (مسحوبة ضوئياً) 📖",
    "file_size_mb": 1.392068862915039,
    "trivia_options": [],
    "post_url": "https://t.me/ReadWorldPDF/7795",
    "msg_id": 7794,
    "file_hash": "272632f610c64030cca73c057fb79548",
    "original_filename": "الأموات - جيمس جويس - @ReadWorldPDF.zip",
    "text_fingerprint": "",
    "timestamp": "2026-06-29T11:05:47.783391",
    "is_pushed": false
}